setup.py
johlsonsunnyday/__init__.py
johlsonsunnyday/johlsonsunnyday.py
johlsonsunnyday.egg-info/PKG-INFO
johlsonsunnyday.egg-info/SOURCES.txt
johlsonsunnyday.egg-info/dependency_links.txt
johlsonsunnyday.egg-info/requires.txt
johlsonsunnyday.egg-info/top_level.txt